README.md
setup.py
src/bap/__init__.py
src/bap/adt.py
src/bap/arm.py
src/bap/asm.py
src/bap/bap.py
src/bap/bil.py
src/bap/bir.py
src/bap/noeval_parser.py
src/bap/rpc.py
src/bap.egg-info/PKG-INFO
src/bap.egg-info/SOURCES.txt
src/bap.egg-info/dependency_links.txt
src/bap.egg-info/requires.txt
src/bap.egg-info/top_level.txt