Metadata-Version: 1.1
Name: bap
Version: 1.3.1
Summary: Python bindings to Binary Analysis Platform (BAP)
Home-page: https://github.com/BinaryAnalysisPlatform/bap-python
Author: Ivan Gotovchits
Author-email: ivg@ieee.org
License: MIT
Platform: UNKNOWN
Classifier: Development Status :: 3 - Alpha
Classifier: License :: OSI Approved :: MIT License
Classifier: Topic :: Software Development :: Disassemblers
Classifier: Topic :: Security
